awsservicespkg/__init__.py
awsservicespkg/alb_service.py
awsservicespkg/backup_service.py
awsservicespkg/cloudformation_service.py
awsservicespkg/ec2_service.py
awsservicespkg/efs_service.py
awsservicespkg/iam_service.py
awsservicespkg/logger.py
awsservicespkg/rds_service.py
awsservicespkg/route53_service.py
awsservicespkg/s3_service.py
awsservicespkg/session.py
awsservicespkg/sns_service.py
awsservicespkg/ssm_service.py
awsservicespkg/sts_service.py
awsservicespkg/utils/__init__.py
awsservicespkg/utils/constants.py
awsservicespkg/utils/utilities.py
awsservicespkg-0.0.0.dist-info/METADATA
awsservicespkg-0.0.0.dist-info/WHEEL
awsservicespkg-0.0.0.dist-info/top_level.txt
awsservicespkg-0.0.0.dist-info/RECORD
